garpix_package/MANIFEST.in
garpix_package/__init__.py
garpix_package/apps.py
garpix_package/setup.py
garpix_package/__pycache__/__init__.cpython-38.pyc
garpix_package/__pycache__/apps.cpython-38.pyc
garpix_package/management/__init__.py
garpix_package/management/__pycache__/__init__.cpython-38.pyc
garpix_package/management/commands/__init__.py
garpix_package/management/commands/pack.py
garpix_package/management/commands/startpackage.py
garpix_package-2.0.1.dist-info/METADATA
garpix_package-2.0.1.dist-info/WHEEL
garpix_package-2.0.1.dist-info/top_level.txt
garpix_package-2.0.1.dist-info/RECORD
