Metadata-Version: 2.1
Name: garpix-package
Version: 2.0.1
Summary: UNKNOWN
Home-page: https://github.com/garpixcms/garpix_package
Author: Garpix LTD
Author-email: info@garpix.com
License: MIT
Platform: UNKNOWN
Classifier: Development Status :: 4 - Beta
Classifier: Environment :: Web Environment
Classifier: Intended Audience :: Developers
Classifier: License :: OSI Approved :: MIT License
Classifier: Operating System :: OS Independent
Classifier: Programming Language :: Python
Classifier: Framework :: Django
Classifier: Programming Language :: Python :: 3.8
Requires-Dist: m2r (==0.2.1)
Requires-Dist: twine (==3.4.1)
Requires-Dist: mistune (==0.8.4)
